sphinx_console-1.0.12-py3.9-nspkg.pth
sphinx_console/__init__.py
sphinx_console/__main__.py
sphinx_console/bash.py
sphinx_console/execute.py
sphinx_console/python.py
sphinx_console/validators.py
sphinxcontrib/console/__init__.py
sphinxcontrib/console/__main__.py
sphinxcontrib/console/bash.py
sphinxcontrib/console/directive.py
sphinxcontrib/console/disassembly.py
sphinxcontrib/console/execute.py
sphinxcontrib/console/python.py
sphinxcontrib/console/sphinx_console.css
sphinxcontrib/console/utilities.py
sphinxcontrib/console/validators.py
sphinx_console-1.0.12.dist-info/LICENSE
sphinx_console-1.0.12.dist-info/METADATA
sphinx_console-1.0.12.dist-info/WHEEL
sphinx_console-1.0.12.dist-info/namespace_packages.txt
sphinx_console-1.0.12.dist-info/top_level.txt
sphinx_console-1.0.12.dist-info/RECORD
