Metadata-Version: 2.1
Name: sphinx-console
Version: 1.0.12
Summary: an extension for sphinx to display console in sphinx documents
Home-page: https://github.com/zqmillet/sphinx-console
Author: kinopico
Author-email: zqmillet@qq.com
License: UNKNOWN
Platform: UNKNOWN
License-File: LICENSE
Requires-Dist: ansi2html (==1.7.0)
Requires-Dist: beautifulsoup4 (==4.11.1)
Requires-Dist: colorama (==0.4.4)
Requires-Dist: css-inline (==0.10.1)
Requires-Dist: docutils (==0.17.1)
Requires-Dist: mezmorize (==0.28.2)
Requires-Dist: pexpect (==4.8.0)
Requires-Dist: Sphinx (==4.4.0)
Requires-Dist: wexpect
